mirai_extensions/trigger/__init__.py
mirai_extensions/trigger/filter.py
mirai_extensions/trigger/handler.py
mirai_extensions/trigger/interrupt.py
mirai_extensions/trigger/message.py
mirai_extensions/trigger/trigger.py
yiri_mirai_trigger-0.3.1.dist-info/LICENSE
yiri_mirai_trigger-0.3.1.dist-info/WHEEL
yiri_mirai_trigger-0.3.1.dist-info/METADATA
yiri_mirai_trigger-0.3.1.dist-info/RECORD
