Metadata-Version: 2.1
Name: yiri-mirai-trigger
Version: 0.3.1
Summary: [YiriMirai] 事件触发器：提供更多处理事件的方式。
License: AGPL-3.0
Author: 忘忧北萱草
Author-email: wybxc@qq.com
Requires-Python: >=3.7,<4.0
Classifier: License :: OSI Approved :: GNU Affero General Public License v3
Classifier: Programming Language :: Python :: 3
Classifier: Programming Language :: Python :: 3.7
Classifier: Programming Language :: Python :: 3.8
Classifier: Programming Language :: Python :: 3.9
Requires-Dist: yiri-mirai (>=0.2.0)
